unilever_map_lib/__init__.py
unilever_map_lib/mapping.py
unilever_map_lib-0.0.2.dist-info/LICENSE
unilever_map_lib-0.0.2.dist-info/METADATA
unilever_map_lib-0.0.2.dist-info/WHEEL
unilever_map_lib-0.0.2.dist-info/top_level.txt
unilever_map_lib-0.0.2.dist-info/RECORD
